koopa_viz/__init__.py
koopa_viz/_widget.py
koopa_viz/napari.yaml
koopa_viz/_tests/__init__.py
koopa_viz/_tests/test_widget.py
koopa_viz-0.0.1.dist-info/LICENSE
koopa_viz-0.0.1.dist-info/METADATA
koopa_viz-0.0.1.dist-info/WHEEL
koopa_viz-0.0.1.dist-info/entry_points.txt
koopa_viz-0.0.1.dist-info/top_level.txt
koopa_viz-0.0.1.dist-info/RECORD
