Metadata-Version: 2.1
Name: koopa-viz
Version: 0.0.1
Summary: Vizualization plugin for koopa image analysis
Home-page: https://github.com/bbquercus/koopa-viz
Author: Bastian Eichenberger
Author-email: bastian@eichenbergers.ch
License: MIT
Project-URL: Bug Tracker, https://github.com/bbquercus/koopa-viz/issues
Project-URL: Documentation, https://github.com/bbquercus/koopa-viz#README.md
Project-URL: Source Code, https://github.com/bbquercus/koopa-viz
Project-URL: User Support, https://github.com/bbquercus/koopa-viz/issues
Classifier: Development Status :: 2 - Pre-Alpha
Classifier: Framework :: napari
Classifier: Intended Audience :: Developers
Classifier: License :: OSI Approved :: MIT License
Classifier: Operating System :: OS Independent
Classifier: Programming Language :: Python
Classifier: Programming Language :: Python :: 3
Classifier: Programming Language :: Python :: 3 :: Only
Classifier: Programming Language :: Python :: 3.8
Classifier: Programming Language :: Python :: 3.9
Classifier: Programming Language :: Python :: 3.10
Classifier: Topic :: Scientific/Engineering :: Image Processing
Requires-Python: >=3.8
License-File: LICENSE
Requires-Dist: numpy
Requires-Dist: pandas
Requires-Dist: pyarrow
Requires-Dist: qtpy
Requires-Dist: scikit-image
Requires-Dist: tifffile
Requires-Dist: trackpy
Provides-Extra: testing
Requires-Dist: tox ; extra == 'testing'
Requires-Dist: pytest ; extra == 'testing'
Requires-Dist: pytest-cov ; extra == 'testing'
Requires-Dist: pytest-qt ; extra == 'testing'
Requires-Dist: napari ; extra == 'testing'
Requires-Dist: pyqt5 ; extra == 'testing'
